AUTHORS
CMakeLists.txt
LICENSE
MANIFEST.in
Makefile
README.rst
VERSION
pyproject.toml
setup.py
site_cfg_template.py
doc/Makefile
doc/archived_news.rst
doc/archived_support.rst
doc/conf.py
doc/dev_info.rst
doc/dev_topics.rst
doc/developer_guide.rst
doc/development.rst
doc/documentation.rst
doc/downloads.rst
doc/doxygen.config
doc/doxygenrc
doc/ebcs_implementation.rst
doc/examples.rst
doc/faq.rst
doc/field_table.rst
doc/index.rst
doc/installation.rst
doc/introduction.rst
doc/license.rst
doc/linear_combination_bc.rst
doc/links.inc
doc/make.bat
doc/man-sfepy-run.rst
doc/man-sfepy-view.rst
doc/mat_optim.rst
doc/multiproc_mpi.log
doc/news.rst
doc/preprocessing.rst
doc/primer.rst
doc/problem_desc_file_long.rst
doc/release_notes.rst
doc/release_tasks.rst
doc/solver_table.rst
doc/solving_pdes_by_fem.rst
doc/splinebox.rst
doc/term_table.rst
doc/terms_overview.rst
doc/test_install.log
doc/theory.rst
doc/tutorial.rst
doc/users_guide.rst
doc/using_salome.rst
doc/_static/sfepy.css
doc/_static/sfepy_logo.png
doc/_static/sfepy_sphinx2_fix.css
doc/_static/uwb_logo.png
doc/_templates/layout.html
doc/examples/acoustics-acoustics.rst
doc/examples/acoustics-acoustics3d.rst
doc/examples/acoustics-helmholtz_apartment.rst
doc/examples/acoustics-index.rst
doc/examples/acoustics-vibro_acoustic3d.rst
doc/examples/dg-advection_1D.rst
doc/examples/dg-advection_2D.rst
doc/examples/dg-advection_diffusion_2D.rst
doc/examples/dg-burgers_2D.rst
doc/examples/dg-dg_plot_1D.rst
doc/examples/dg-example_dg_common.rst
doc/examples/dg-imperative_burgers_1D.rst
doc/examples/dg-index.rst
doc/examples/dg-laplace_2D.rst
doc/examples/diffusion-cube.rst
doc/examples/diffusion-darcy_flow_multicomp.rst
doc/examples/diffusion-index.rst
doc/examples/diffusion-laplace_1d.rst
doc/examples/diffusion-laplace_coupling_lcbcs.rst
doc/examples/diffusion-laplace_fluid_2d.rst
doc/examples/diffusion-laplace_iga_interactive.rst
doc/examples/diffusion-laplace_refine_interactive.rst
sfepy.egg-info/PKG-INFO
sfepy.egg-info/SOURCES.txt
sfepy.egg-info/dependency_links.txt
sfepy.egg-info/entry_points.txt
sfepy.egg-info/requires.txt
sfepy.egg-info/top_level.txt
